{
  "aor": 0.0034579045092838203,
  "aqi": 0.010933878196286474,
  "bids_meta": {
    "dataset": "ds003020",
    "modality": "bold",
    "session_id": "3",
    "subject_id": "UTS08",
    "task_id": "myfirstdaywiththeyankees"
  },
  "dummy_trs": 1,
  "dvars_nstd": 30.774829433191467,
  "dvars_std": 1.3481876450000003,
  "dvars_vstd": 0.9603038640425534,
  "efc": 0.48495997289186205,
  "fber": 46350.33984375,
  "fd_mean": 0.15637462804961702,
  "fd_num": 80,
  "fd_perc": 21.220159151193634,
  "fwhm_avg": 1.8453883057568226,
  "fwhm_x": 1.7485783484765975,
  "fwhm_y": 1.9821174373609591,
  "fwhm_z": 1.805469131432911,
  "gcor": 0.0154813,
  "gsr_x": -0.0009039577562361956,
  "gsr_y": 0.018045401200652122,
  "provenance": {
    "md5sum": "03c04ebcd3f1f5079710ad0cbca4e087",
    "settings": {
      "fd_thres": 0.2,
      "testing": false
    },
    "software": "mriqc",
    "version": "23.0.1",
    "webapi_port": null,
    "webapi_url": "https://mriqc.nimh.nih.gov/api/v1"
  },
  "size_t": 377,
  "size_x": 84,
  "size_y": 84,
  "size_z": 54,
  "snr": 5.017559739614567,
  "spacing_tr": 2.0,
  "spacing_x": 2.6190476417541504,
  "spacing_y": 2.6190476417541504,
  "spacing_z": 2.6000001430511475,
  "summary_bg_k": 19.40340737133322,
  "summary_bg_mad": 163.40643321159553,
  "summary_bg_mean": 1133.4404296875,
  "summary_bg_median": 136.14303588867188,
  "summary_bg_n": 248254.0,
  "summary_bg_p05": 16.079183197021486,
  "summary_bg_p95": 5875.736474609366,
  "summary_bg_stdv": 2605.88232421875,
  "summary_fg_k": 2.3215589283412044,
  "summary_fg_mad": 5417.980138690222,
  "summary_fg_mean": 30412.876953125,
  "summary_fg_median": 29733.703125,
  "summary_fg_n": 71612.0,
  "summary_fg_p05": 22797.65068359375,
  "summary_fg_p95": 40550.53867187499,
  "summary_fg_stdv": 5925.8876953125,
  "tsnr": 54.076873779296875
}