{
  "aor": 0.002618828828828829,
  "aqi": 0.007547935135135134,
  "bids_meta": {
    "dataset": "ds003020",
    "modality": "bold",
    "session_id": "5",
    "subject_id": "UTS08",
    "task_id": "theclosetthatateeverything"
  },
  "dummy_trs": 1,
  "dvars_nstd": 31.889654538584352,
  "dvars_std": 1.4112279064156625,
  "dvars_vstd": 1.0289186728313258,
  "efc": 0.4847688109588266,
  "fber": 56805.2578125,
  "fd_mean": 0.18336588915529037,
  "fd_num": 112,
  "fd_perc": 33.633633633633636,
  "fwhm_avg": 1.8354807348811466,
  "fwhm_x": 1.74506180305254,
  "fwhm_y": 1.9645843466038762,
  "fwhm_z": 1.7967960549870239,
  "gcor": 0.018678,
  "gsr_x": -7.612851914018393e-05,
  "gsr_y": 0.01922881416976452,
  "provenance": {
    "md5sum": "1fddd2db11c4efe78350543a8ff6a80f",
    "settings": {
      "fd_thres": 0.2,
      "testing": false
    },
    "software": "mriqc",
    "version": "23.0.1",
    "webapi_port": null,
    "webapi_url": "https://mriqc.nimh.nih.gov/api/v1"
  },
  "size_t": 333,
  "size_x": 84,
  "size_y": 84,
  "size_z": 54,
  "snr": 4.992794374333269,
  "spacing_tr": 2.0,
  "spacing_x": 2.6190476417541504,
  "spacing_y": 2.6190476417541504,
  "spacing_z": 2.6000001430511475,
  "summary_bg_k": 19.983094369145967,
  "summary_bg_mad": 134.6578410848674,
  "summary_bg_mean": 1126.0732421875,
  "summary_bg_median": 121.68998718261719,
  "summary_bg_n": 248194.0,
  "summary_bg_p05": 26.213055992126463,
  "summary_bg_p95": 5875.237060546861,
  "summary_bg_stdv": 2639.97216796875,
  "summary_fg_k": 2.1531519853888934,
  "summary_fg_mad": 5519.099690977966,
  "summary_fg_mean": 30334.271484375,
  "summary_fg_median": 29688.8984375,
  "summary_fg_n": 71637.0,
  "summary_fg_p05": 22672.233203125,
  "summary_fg_p95": 40555.64921875,
  "summary_fg_stdv": 5946.3076171875,
  "tsnr": 62.71274185180664
}