{
  "aor": 0.0005254269972451791,
  "aqi": 0.005324929173553719,
  "bids_meta": {
    "dataset": "ds003020",
    "modality": "bold",
    "session_id": "2",
    "subject_id": "UTS03",
    "task_id": "alternateithicatom"
  },
  "dummy_trs": 0,
  "dvars_nstd": 20.425959479005524,
  "dvars_std": 1.2572836178729299,
  "dvars_vstd": 0.9777336087292808,
  "efc": 0.4733277492609804,
  "fber": 81809.75,
  "fd_mean": 0.04465640439616856,
  "fd_num": 0,
  "fd_perc": 0.0,
  "fwhm_avg": 1.8251550090771531,
  "fwhm_x": 1.6862274399262565,
  "fwhm_y": 1.9877759827664463,
  "fwhm_z": 1.8014616045387561,
  "gcor": 0.0416201,
  "gsr_x": -0.005419908557087183,
  "gsr_y": 0.04177200421690941,
  "provenance": {
    "md5sum": "66f2d3504357e0218ae6a67ee34202e0",
    "settings": {
      "fd_thres": 0.2,
      "testing": false
    },
    "software": "mriqc",
    "version": "23.0.1",
    "webapi_port": null,
    "webapi_url": "https://mriqc.nimh.nih.gov/api/v1"
  },
  "size_t": 363,
  "size_x": 84,
  "size_y": 84,
  "size_z": 54,
  "snr": 5.954780504438328,
  "spacing_tr": 2.0,
  "spacing_x": 2.6190476417541504,
  "spacing_y": 2.6190476417541504,
  "spacing_z": 2.5999999046325684,
  "summary_bg_k": 42.065859469064584,
  "summary_bg_mad": 103.20132982547662,
  "summary_bg_mean": 1034.5550537109375,
  "summary_bg_median": 97.92251586914062,
  "summary_bg_n": 255010.0,
  "summary_bg_p05": 24.595049476623537,
  "summary_bg_p95": 5444.404150390625,
  "summary_bg_stdv": 2472.96044921875,
  "summary_fg_k": 2.2767939591534736,
  "summary_fg_mad": 4492.267347827225,
  "summary_fg_mean": 28636.0,
  "summary_fg_median": 28458.5703125,
  "summary_fg_n": 66220.0,
  "summary_fg_p05": 21651.1912109375,
  "summary_fg_p95": 36252.949414062496,
  "summary_fg_stdv": 4779.0771484375,
  "tsnr": 75.21439361572266
}