{
  "bids_meta": {
    "dataset": "ds003020",
    "modality": "T1w",
    "session_id": "1",
    "subject_id": "UTS04"
  },
  "cjv": 0.33013261271093414,
  "cnr": 2.426541563334905,
  "efc": 0.7993770789040026,
  "fber": 4.7054760257825965,
  "fwhm_avg": 3.62861,
  "fwhm_x": 3.72488,
  "fwhm_y": 3.69817,
  "fwhm_z": 3.46278,
  "icvs_csf": 0.2882117491583486,
  "icvs_gm": 0.3930537180320123,
  "icvs_wm": 0.31873453280963915,
  "inu_med": 0.265641450881958,
  "inu_range": 0.013953745365142822,
  "provenance": {
    "md5sum": "7bbe2aab8015b62102f99924ee1d94a8",
    "settings": {
      "testing": false
    },
    "software": "mriqc",
    "version": "23.0.1",
    "warnings": {
      "large_rot_frame": true,
      "small_air_mask": true
    },
    "webapi_port": null,
    "webapi_url": "https://mriqc.nimh.nih.gov/api/v1"
  },
  "qi_1": 0.0,
  "qi_2": 0.0032132122318829963,
  "rpve_csf": 22.48342464343001,
  "rpve_gm": 14.691732049727863,
  "rpve_wm": 27.091688115506052,
  "size_x": 256,
  "size_y": 256,
  "size_z": 256,
  "snr_csf": 2.5902865680254106,
  "snr_gm": 5.15000260052008,
  "snr_total": 38.693090098994354,
  "snr_wm": 108.33898112843757,
  "snrd_csf": -1.0,
  "snrd_gm": -1.0,
  "snrd_total": -1.0,
  "snrd_wm": -1.0,
  "spacing_x": 1.0,
  "spacing_y": 1.0,
  "spacing_z": 1.0,
  "summary_bg_k": 0.0,
  "summary_bg_mad": 0.0,
  "summary_bg_mean": 0.0,
  "summary_bg_median": 0.0,
  "summary_bg_n": 0.0,
  "summary_bg_p05": 0.0,
  "summary_bg_p95": 0.0,
  "summary_bg_stdv": 0.0,
  "summary_csf_k": 0.4458244761093657,
  "summary_csf_mad": 98.24543546849955,
  "summary_csf_mean": 260.023725390465,
  "summary_csf_median": 258.9791100025177,
  "summary_csf_n": 12610.0,
  "summary_csf_p05": 102.75059664621949,
  "summary_csf_p95": 425.3901149183512,
  "summary_csf_stdv": 99.97690765055751,
  "summary_gm_k": 14.17741264447195,
  "summary_gm_mad": 97.75528661862677,
  "summary_gm_mean": 692.5325872810657,
  "summary_gm_median": 679.2383070960641,
  "summary_gm_n": 23037.0,
  "summary_gm_p05": 517.8259798549116,
  "summary_gm_p95": 880.7246894307435,
  "summary_gm_stdv": 131.8880041989217,
  "summary_wm_k": 1.3084620932523476,
  "summary_wm_mad": 8.156076861883019,
  "summary_wm_mean": 1001.3749502670779,
  "summary_wm_median": 1000.0529112964869,
  "summary_wm_n": 163052.0,
  "summary_wm_p05": 989.1034268662333,
  "summary_wm_p95": 1019.2806291244924,
  "summary_wm_stdv": 9.230748103838696,
  "tpm_overlap_csf": 0.1390068923752354,
  "tpm_overlap_gm": 0.42374375584964624,
  "tpm_overlap_wm": 0.48768000157393326,
  "wm2max": 0.6634848218985787
}