{
  "aor": 0.0015634405144694533,
  "aqi": 0.00516900807073955,
  "bids_meta": {
    "dataset": "ds003020",
    "modality": "bold",
    "run_id": 1,
    "session_id": "2",
    "subject_id": "UTS05",
    "task_id": "wheretheressmoke"
  },
  "dummy_trs": 0,
  "dvars_nstd": 27.038220743935476,
  "dvars_std": 1.4147173737096779,
  "dvars_vstd": 1.021382382483871,
  "efc": 0.47071371524124705,
  "fber": 132956.984375,
  "fd_mean": 0.06992580184128068,
  "fd_num": 1,
  "fd_perc": 0.3215434083601286,
  "fwhm_avg": 1.7670793726705567,
  "fwhm_x": 1.645563803915164,
  "fwhm_y": 1.8903627108837238,
  "fwhm_z": 1.7653116032127822,
  "gcor": 0.0415756,
  "gsr_x": -0.01287086121737957,
  "gsr_y": 0.04121135547757149,
  "provenance": {
    "md5sum": "f145e887be424bd2941c3d9e5432eb83",
    "settings": {
      "fd_thres": 0.2,
      "testing": false
    },
    "software": "mriqc",
    "version": "23.0.1",
    "webapi_port": null,
    "webapi_url": "https://mriqc.nimh.nih.gov/api/v1"
  },
  "size_t": 311,
  "size_x": 84,
  "size_y": 84,
  "size_z": 54,
  "snr": 6.117423204761807,
  "spacing_tr": 2.0,
  "spacing_x": 2.6190476417541504,
  "spacing_y": 2.6190476417541504,
  "spacing_z": 2.5999999046325684,
  "summary_bg_k": 29.62575394987695,
  "summary_bg_mad": 64.17231026662336,
  "summary_bg_mean": 803.0966186523438,
  "summary_bg_median": 72.4319076538086,
  "summary_bg_n": 252227.0,
  "summary_bg_p05": 24.464845275878908,
  "summary_bg_p95": 4326.178906249999,
  "summary_bg_stdv": 2111.91015625,
  "summary_fg_k": 1.6873748858102493,
  "summary_fg_mad": 4422.503963748638,
  "summary_fg_mean": 26983.880859375,
  "summary_fg_median": 26841.140625,
  "summary_fg_n": 69327.0,
  "summary_fg_p05": 20664.530078125,
  "summary_fg_p95": 33913.981640624996,
  "summary_fg_stdv": 4387.623046875,
  "tsnr": 80.85350799560547
}